LICENSE.txt
README.md
pyproject.toml
setup.cfg
setup.py
src/cleancourt/__init__.py
src/cleancourt/check_spaces.py
src/cleancourt/clean_data.py
src/cleancourt/compare_companies.py
src/cleancourt/compute_ngrams.py
src/cleancourt/cosine_similarity.py
src/cleancourt/filter_types.py
src/cleancourt/full_clean_names.py
src/cleancourt/integrate_output.py
src/cleancourt/parse_names.py
src/cleancourt/separate_parent_company.py
src/cleancourt/test_utils.py
src/cleancourt.egg-info/PKG-INFO
src/cleancourt.egg-info/SOURCES.txt
src/cleancourt.egg-info/dependency_links.txt
src/cleancourt.egg-info/requires.txt
src/cleancourt.egg-info/top_level.txt